looloo_mypackage/__init__.py
looloo_mypackage/mypackage.py
looloo_mypackage-0.0.2.dist-info/LICENSE
looloo_mypackage-0.0.2.dist-info/METADATA
looloo_mypackage-0.0.2.dist-info/WHEEL
looloo_mypackage-0.0.2.dist-info/top_level.txt
looloo_mypackage-0.0.2.dist-info/RECORD
